nltk/VERSION
nltk/__init__.py
nltk/book.py
nltk/cli.py
nltk/collections.py
nltk/collocations.py
nltk/compat.py
nltk/data.py
nltk/decorators.py
nltk/downloader.py
nltk/featstruct.py
nltk/grammar.py
nltk/help.py
nltk/internals.py
nltk/jsontags.py
nltk/langnames.py
nltk/lazyimport.py
nltk/probability.py
nltk/tabdata.py
nltk/text.py
nltk/tgrep.py
nltk/toolbox.py
nltk/treeprettyprinter.py
nltk/treetransforms.py
nltk/util.py
nltk/wsd.py
nltk/app/__init__.py
nltk/app/chartparser_app.py
nltk/app/chunkparser_app.py
nltk/app/collocations_app.py
nltk/app/concordance_app.py
nltk/app/nemo_app.py
nltk/app/rdparser_app.py
nltk/app/srparser_app.py
nltk/app/wordfreq_app.py
nltk/app/wordnet_app.py
nltk/ccg/__init__.py
nltk/ccg/api.py
nltk/ccg/chart.py
nltk/ccg/combinator.py
nltk/ccg/lexicon.py
nltk/ccg/logic.py
nltk/chat/__init__.py
nltk/chat/eliza.py
nltk/chat/iesha.py
nltk/chat/rude.py
nltk/chat/suntsu.py
nltk/chat/util.py
nltk/chat/zen.py
nltk/chunk/__init__.py
nltk/chunk/api.py
nltk/chunk/named_entity.py
nltk/chunk/regexp.py
nltk/chunk/util.py
nltk/classify/__init__.py
nltk/classify/api.py
nltk/classify/decisiontree.py
nltk/classify/maxent.py
nltk/classify/megam.py
nltk/classify/naivebayes.py
nltk/classify/positivenaivebayes.py
nltk/classify/rte_classify.py
nltk/classify/scikitlearn.py
nltk/classify/senna.py
nltk/classify/svm.py
nltk/classify/tadm.py
nltk/classify/textcat.py
nltk/classify/util.py
nltk/classify/weka.py
nltk/cluster/__init__.py
nltk/cluster/api.py
nltk/cluster/em.py
nltk/cluster/gaac.py
nltk/cluster/kmeans.py
nltk/cluster/util.py
nltk/corpus/__init__.py
nltk/corpus/europarl_raw.py
nltk/corpus/util.py
nltk/corpus/reader/__init__.py
nltk/corpus/reader/aligned.py
nltk/corpus/reader/api.py
nltk/corpus/reader/bcp47.py
nltk/corpus/reader/bnc.py
nltk/corpus/reader/bracket_parse.py
nltk/corpus/reader/categorized_sents.py
nltk/corpus/reader/chasen.py
nltk/corpus/reader/childes.py
nltk/corpus/reader/chunked.py
nltk/corpus/reader/cmudict.py
nltk-3.9.dist-info/AUTHORS.md
nltk-3.9.dist-info/LICENSE.txt
nltk-3.9.dist-info/METADATA
nltk-3.9.dist-info/README.md
nltk-3.9.dist-info/WHEEL
nltk-3.9.dist-info/entry_points.txt
nltk-3.9.dist-info/top_level.txt
nltk-3.9.dist-info/RECORD
